odoo/addons/stock_picking_show_lot/README.rst
odoo/addons/stock_picking_show_lot/__init__.py
odoo/addons/stock_picking_show_lot/__manifest__.py
odoo/addons/stock_picking_show_lot/i18n/es_ES.po
odoo/addons/stock_picking_show_lot/i18n/stock_picking_show_lot .pot
odoo/addons/stock_picking_show_lot/i18n/stock_picking_show_lot.pot
odoo/addons/stock_picking_show_lot/models/__init__.py
odoo/addons/stock_picking_show_lot/models/stock_picking.py
odoo/addons/stock_picking_show_lot/readme/CONTRIBUTORS.rst
odoo/addons/stock_picking_show_lot/readme/DESCRIPTION.rst
odoo/addons/stock_picking_show_lot/static/description/icon.png
odoo/addons/stock_picking_show_lot/static/description/index.html
odoo/addons/stock_picking_show_lot/views/stock_picking_views.xml
odoo_addon_stock_picking_show_lot-15.0.1.0.0.1.dist-info/METADATA
odoo_addon_stock_picking_show_lot-15.0.1.0.0.1.dist-info/WHEEL
odoo_addon_stock_picking_show_lot-15.0.1.0.0.1.dist-info/top_level.txt
odoo_addon_stock_picking_show_lot-15.0.1.0.0.1.dist-info/RECORD
